LICENSE
MANIFEST.in
README.md
requirements.txt
setup.cfg
setup.py
telegraph_commander/__init__.py
telegraph_commander/bot.py
telegraph_commander/command.py
telegraph_commander/config.py
telegraph_commander/logger.py
telegraph_commander/redis.py
telegraph_commander/singleton.py
telegraph_commander/telegram.py
telegraph_commander.egg-info/PKG-INFO
telegraph_commander.egg-info/SOURCES.txt
telegraph_commander.egg-info/dependency_links.txt
telegraph_commander.egg-info/requires.txt
telegraph_commander.egg-info/top_level.txt