Metadata-Version: 1.1
Name: telegraph-commander
Version: 0.0.3
Summary: Telegram Bot framework
Home-page: https://github.com/harlov/telegraph_commander
Author: Nikita Harlov
Author-email: nikita@harlov.com
License: MTI License
Download-URL: https://github.com/harlov/telegraph_commander/archive/v0.0.3.tar.gz
Platform: UNKNOWN
Classifier: Environment :: Console
Classifier: Intended Audience :: Developers
Classifier: License :: OSI Approved :: MIT License
Classifier: Operating System :: OS Independent
Classifier: Programming Language :: Python
Classifier: Programming Language :: Python :: 3
Classifier: Programming Language :: Python :: 3.5
Classifier: Topic :: Education
